perceptron/__init__.py
perceptron/mlp.py
perceptron/lib/__init__.py
perceptron/lib/db.py
perceptron/lib/trainer.py
perceptron/lib/utils.py
perceptron-1.1.0.dist-info/DESCRIPTION.rst
perceptron-1.1.0.dist-info/METADATA
perceptron-1.1.0.dist-info/RECORD
perceptron-1.1.0.dist-info/WHEEL
perceptron-1.1.0.dist-info/metadata.json
perceptron-1.1.0.dist-info/top_level.txt
