Metadata-Version: 2.0
Name: perceptron
Version: 1.1.0
Summary: Multilayer perceptron network implementation in Python
Home-page: https://github.com/rfguri/perceptron/
Author: Roger Fernandez Guri
Author-email: rfguri@gmail.com
License: The MIT License (MIT)
